{
    "boot": "workspace",
    "engine": [
        "node"
    ],
    "packages": {
        "workspace": {
            "locator": {
                "location": "./"
            }
        },
        "nodejs.org/": {
            "provider": "nodejs.org/"
        },
        "pinf.org/loader/": {
            "provider": "pinf.org/loader/"
        },
        "github.com/pinf/modules-js/": {
            "locator": {
                "archive": "https://github.com/pinf/modules-js/zipball/master"
            }
        },
        "github.com/kriskowal/q/": {
            "locator": {
                "archive": "https://github.com/kriskowal/q/zipball/v0.3.0"
            },
            "descriptor": {
                "uid": "https://github.com/kriskowal/q/",
                "dependencies": [
                    {
                        "id": "github.com/pinf/modules-js/"
                    }
                ]
            }
        },
        "private-registry.appspot.com/cadorn.com/github/com.cadorn.baby/projects/sourcemint/packages/client-js/": {
            "locator": {
                "archive": "https://github.com/cadorn/com.cadorn.baby/zipball/master",
                "path": "projects/sourcemint/packages/client-js"
            }
        },
        "github.com/cadorn/aws-lib/": {
            "locator": {
                "archive": "https://github.com/cadorn/aws-lib/zipball/master"
            },
            "descriptor": {
                "uid": "https://github.com/cadorn/aws-lib/",
                "native": true,
                "dependencies": [
                    {
                        "id": "registry.npmjs.org/sax/"
                    },
                    {
                        "id": "registry.npmjs.org/xml2js/"
                    }
                ]
            }
        },
        "registry.npmjs.org/sax/": {
            "locator": {
                "archive": "http://registry.npmjs.org/sax/-/sax-0.1.2.tgz"
            },
            "descriptor": {
                "uid": "http://registry.npmjs.org/sax/",
                "native": true
            }
        },
        "registry.npmjs.org/xml2js/": {
            "locator": {
                "archive": "http://registry.npmjs.org/xml2js/-/xml2js-0.1.6.tgz"
            },
            "descriptor": {
                "uid": "http://registry.npmjs.org/xml2js/",
                "native": true
            }
        }
    }
}